marque/__init__.py
marque/flow.py
marque/helpers.py
marque/logging.py
marque/py.typed
marque/scope.py
marque/storage.py
marque/util.py
marque-0.1.1.dist-info/LICENSE
marque-0.1.1.dist-info/METADATA
marque-0.1.1.dist-info/WHEEL
marque-0.1.1.dist-info/RECORD
