Metadata-Version: 2.1
Name: marque
Version: 0.1.1
Summary: Minimal workflows
Author: Nick Landers
Author-email: monoxgas@gmail.com
Requires-Python: >=3.10,<4.0
Classifier: Programming Language :: Python :: 3
Classifier: Programming Language :: Python :: 3.10
Classifier: Programming Language :: Python :: 3.11
Classifier: Programming Language :: Python :: 3.12
Requires-Dist: coolname (>=2.2.0,<3.0.0)
Requires-Dist: loguru (>=0.7.2,<0.8.0)
Requires-Dist: orjson (>=3.9.12,<4.0.0)
Requires-Dist: polars (>=0.20.5,<0.21.0)
Requires-Dist: pydantic (>=2.6.4,<3.0.0)
